[
  {
    "id": "Channel One",
    "channel": "Channel One",
    "channelImage": "https://api3.viu.lk/api/client/v1/global/images/22849?accessKey=WkVjNWNscFhORDBLCg==",
    "type": "IPTV",
    "epgID": "1",
    "category": "Local",
    "realepgId": 11,
    "title": "Ru Nari",
    "thumbnail": "https://api3.viu.lk/api/client/v1/global/images/34130?accessKey=WkVjNWNscFhORDBLCg==",
    "views": "2 views",
    "time": "LIVE",
    "isLive": true,
    "manifest": "https://api.viulk.xyz/api/api/client/v1/default/users/69/live/channels/channelone"
  },
  {
    "id": "History TV 18",
    "channel": "History TV 18",
    "channelImage": "https://api3.viu.lk/api/client/v1/global/images/22810?accessKey=WkVjNWNscFhORDBLCg==",
    "type": "IPTV",
    "epgID": "61",
    "category": "Other",
    "realepgId": 67,
    "title": "Life After People",
    "thumbnail": "https://api3.viu.lk/api/client/v1/global/images/694436?accessKey=WkVjNWNscFhORDBLCg==",
    "views": "0 views",
    "time": "LIVE",
    "isLive": true,
    "manifest": "https://api.viulk.xyz/api/api/client/v1/default/users/69/live/channels/historytv18"
  },
  {
    "id": "Star Sports 1",
    "channel": "Star Sports 1",
    "channelImage": "https://api3.viu.lk/api/client/v1/global/images/23050?accessKey=WkVjNWNscFhORDBLCg==",
    "type": "IPTV",
    "epgID": "68",
    "category": "Sports",
    "realepgId": 75,
    "title": "ICC Men's T20 WC HLs IND v PAK",
    "thumbnail": "https://api3.viu.lk/api/client/v1/global/images/732725?accessKey=WkVjNWNscFhORDBLCg==",
    "views": "2 views",
    "time": "LIVE",
    "isLive": true,
    "manifest": "https://api.viulk.xyz/api/api/client/v1/default/users/69/live/channels/starsports1"
  },
  {
    "id": "The Papare TV 1",
    "channel": "The Papare TV 1",
    "channelImage": "https://api3.viu.lk/api/client/v1/global/images/130716?accessKey=WkVjNWNscFhORDBLCg==",
    "type": "IPTV",
    "epgID": "62",
    "category": "Sports",
    "realepgId": 2126,
    "title": "Replay -  ICC Men's T20 World Cup 2026",
    "thumbnail": "https://api3.viu.lk/api/client/v1/global/images/733819?accessKey=WkVjNWNscFhORDBLCg==",
    "views": "0 views",
    "time": "LIVE",
    "isLive": true,
    "manifest": "https://api.viulk.xyz/api/api/client/v1/default/users/69/live/channels/paparetv1"
  },
  {
    "id": "The Papare TV 2",
    "channel": "The Papare TV 2",
    "channelImage": "https://api3.viu.lk/api/client/v1/global/images/130718?accessKey=WkVjNWNscFhORDBLCg==",
    "type": "IPTV",
    "epgID": "63",
    "category": "Sports",
    "realepgId": 70,
    "title": "Live - RPL T10 League 2026 - Quarter Finals",
    "thumbnail": "https://api3.viu.lk/api/client/v1/global/images/741184?accessKey=WkVjNWNscFhORDBLCg==",
    "views": "0 views",
    "time": "LIVE",
    "isLive": true,
    "manifest": "https://api.viulk.xyz/api/api/client/v1/default/users/69/live/channels/paparesd"
  },
  
]



